synode.py
synode-0.1.8.dist-info/LICENSE
synode-0.1.8.dist-info/METADATA
synode-0.1.8.dist-info/WHEEL
synode-0.1.8.dist-info/top_level.txt
synode-0.1.8.dist-info/RECORD
