Metadata-Version: 2.1
Name: synode
Version: 0.1.8
Summary: Syntax node Python library for programming languages
Home-page: UNKNOWN
Author: Youngsung Kim
Author-email: grnydawn@gmail.com
License: UNKNOWN
Platform: UNKNOWN
Classifier: Programming Language :: Python :: 3
Classifier: License :: OSI Approved :: MIT License
Classifier: Operating System :: OS Independent
